<annotation>
	<folder>train_splits</folder>
	<filename>gear10n (40)_04_01.png</filename>
	<path>C:\Users\koiralaa\Desktop\ANNOTATIONS\train_splits\gear10n (40)_04_01.png</path>
	<source>
		<database>Unknown</database>
	</source>
	<size>
		<width>612</width>
		<height>512</height>
		<depth>3</depth>
	</size>
	<segmented>0</segmented>
	<object>
		<name>M</name>
		<pose>Unspecified</pose>
		<truncated>0</truncated>
		<difficult>0</difficult>
		<bndbox>
			<xmin>75</xmin>
			<ymin>66</ymin>
			<xmax>124</xmax>
			<ymax>120</ymax>
		</bndbox>
	</object>
	<object>
		<name>M</name>
		<pose>Unspecified</pose>
		<truncated>0</truncated>
		<difficult>0</difficult>
		<bndbox>
			<xmin>185</xmin>
			<ymin>35</ymin>
			<xmax>228</xmax>
			<ymax>86</ymax>
		</bndbox>
	</object>
	<object>
		<name>M</name>
		<pose>Unspecified</pose>
		<truncated>0</truncated>
		<difficult>0</difficult>
		<bndbox>
			<xmin>223</xmin>
			<ymin>35</ymin>
			<xmax>257</xmax>
			<ymax>87</ymax>
		</bndbox>
	</object>
</annotation>
