<annotation>
	<folder>train_splits</folder>
	<filename>gear8s (61)_04_04.png</filename>
	<path>C:\Users\koiralaa\Desktop\ANNOTATIONS\train_splits\gear8s (61)_04_04.png</path>
	<source>
		<database>Unknown</database>
	</source>
	<size>
		<width>612</width>
		<height>512</height>
		<depth>3</depth>
	</size>
	<segmented>0</segmented>
	<object>
		<name>M</name>
		<pose>Unspecified</pose>
		<truncated>0</truncated>
		<difficult>0</difficult>
		<bndbox>
			<xmin>462</xmin>
			<ymin>105</ymin>
			<xmax>527</xmax>
			<ymax>167</ymax>
		</bndbox>
	</object>
	<object>
		<name>M</name>
		<pose>Unspecified</pose>
		<truncated>0</truncated>
		<difficult>0</difficult>
		<bndbox>
			<xmin>467</xmin>
			<ymin>150</ymin>
			<xmax>519</xmax>
			<ymax>205</ymax>
		</bndbox>
	</object>
	<object>
		<name>M</name>
		<pose>Unspecified</pose>
		<truncated>0</truncated>
		<difficult>0</difficult>
		<bndbox>
			<xmin>482</xmin>
			<ymin>197</ymin>
			<xmax>549</xmax>
			<ymax>264</ymax>
		</bndbox>
	</object>
</annotation>
