<annotation>
	<folder>train_splits</folder>
	<filename>gear8n (61)_03_04.png</filename>
	<path>C:\Users\koiralaa\Desktop\ANNOTATIONS\train_splits\gear8n (61)_03_04.png</path>
	<source>
		<database>Unknown</database>
	</source>
	<size>
		<width>612</width>
		<height>512</height>
		<depth>3</depth>
	</size>
	<segmented>0</segmented>
	<object>
		<name>M</name>
		<pose>Unspecified</pose>
		<truncated>0</truncated>
		<difficult>0</difficult>
		<bndbox>
			<xmin>16</xmin>
			<ymin>111</ymin>
			<xmax>51</xmax>
			<ymax>154</ymax>
		</bndbox>
	</object>
	<object>
		<name>M</name>
		<pose>Unspecified</pose>
		<truncated>1</truncated>
		<difficult>0</difficult>
		<bndbox>
			<xmin>1</xmin>
			<ymin>136</ymin>
			<xmax>26</xmax>
			<ymax>177</ymax>
		</bndbox>
	</object>
	<object>
		<name>M</name>
		<pose>Unspecified</pose>
		<truncated>0</truncated>
		<difficult>0</difficult>
		<bndbox>
			<xmin>19</xmin>
			<ymin>165</ymin>
			<xmax>53</xmax>
			<ymax>201</ymax>
		</bndbox>
	</object>
	<object>
		<name>M</name>
		<pose>Unspecified</pose>
		<truncated>0</truncated>
		<difficult>0</difficult>
		<bndbox>
			<xmin>37</xmin>
			<ymin>187</ymin>
			<xmax>70</xmax>
			<ymax>222</ymax>
		</bndbox>
	</object>
	<object>
		<name>M</name>
		<pose>Unspecified</pose>
		<truncated>0</truncated>
		<difficult>0</difficult>
		<bndbox>
			<xmin>70</xmin>
			<ymin>196</ymin>
			<xmax>105</xmax>
			<ymax>235</ymax>
		</bndbox>
	</object>
	<object>
		<name>M</name>
		<pose>Unspecified</pose>
		<truncated>0</truncated>
		<difficult>0</difficult>
		<bndbox>
			<xmin>68</xmin>
			<ymin>218</ymin>
			<xmax>102</xmax>
			<ymax>242</ymax>
		</bndbox>
	</object>
	<object>
		<name>M</name>
		<pose>Unspecified</pose>
		<truncated>0</truncated>
		<difficult>0</difficult>
		<bndbox>
			<xmin>112</xmin>
			<ymin>162</ymin>
			<xmax>156</xmax>
			<ymax>205</ymax>
		</bndbox>
	</object>
	<object>
		<name>M</name>
		<pose>Unspecified</pose>
		<truncated>0</truncated>
		<difficult>0</difficult>
		<bndbox>
			<xmin>59</xmin>
			<ymin>244</ymin>
			<xmax>99</xmax>
			<ymax>280</ymax>
		</bndbox>
	</object>
	<object>
		<name>M</name>
		<pose>Unspecified</pose>
		<truncated>0</truncated>
		<difficult>0</difficult>
		<bndbox>
			<xmin>105</xmin>
			<ymin>219</ymin>
			<xmax>139</xmax>
			<ymax>255</ymax>
		</bndbox>
	</object>
	<object>
		<name>M</name>
		<pose>Unspecified</pose>
		<truncated>0</truncated>
		<difficult>0</difficult>
		<bndbox>
			<xmin>146</xmin>
			<ymin>242</ymin>
			<xmax>193</xmax>
			<ymax>286</ymax>
		</bndbox>
	</object>
	<object>
		<name>M</name>
		<pose>Unspecified</pose>
		<truncated>0</truncated>
		<difficult>0</difficult>
		<bndbox>
			<xmin>154</xmin>
			<ymin>290</ymin>
			<xmax>196</xmax>
			<ymax>331</ymax>
		</bndbox>
	</object>
</annotation>
