<annotation>
	<folder>train_splits</folder>
	<filename>gear10s (6)_03_03.png</filename>
	<path>C:\Users\koiralaa\Desktop\ANNOTATIONS\train_splits\gear10s (6)_03_03.png</path>
	<source>
		<database>Unknown</database>
	</source>
	<size>
		<width>612</width>
		<height>512</height>
		<depth>3</depth>
	</size>
	<segmented>0</segmented>
	<object>
		<name>M</name>
		<pose>Unspecified</pose>
		<truncated>0</truncated>
		<difficult>0</difficult>
		<bndbox>
			<xmin>142</xmin>
			<ymin>262</ymin>
			<xmax>178</xmax>
			<ymax>304</ymax>
		</bndbox>
	</object>
	<object>
		<name>M</name>
		<pose>Unspecified</pose>
		<truncated>0</truncated>
		<difficult>0</difficult>
		<bndbox>
			<xmin>155</xmin>
			<ymin>278</ymin>
			<xmax>207</xmax>
			<ymax>338</ymax>
		</bndbox>
	</object>
	<object>
		<name>M</name>
		<pose>Unspecified</pose>
		<truncated>0</truncated>
		<difficult>0</difficult>
		<bndbox>
			<xmin>167</xmin>
			<ymin>397</ymin>
			<xmax>200</xmax>
			<ymax>435</ymax>
		</bndbox>
	</object>
	<object>
		<name>M</name>
		<pose>Unspecified</pose>
		<truncated>0</truncated>
		<difficult>0</difficult>
		<bndbox>
			<xmin>195</xmin>
			<ymin>276</ymin>
			<xmax>222</xmax>
			<ymax>315</ymax>
		</bndbox>
	</object>
	<object>
		<name>M</name>
		<pose>Unspecified</pose>
		<truncated>0</truncated>
		<difficult>0</difficult>
		<bndbox>
			<xmin>241</xmin>
			<ymin>390</ymin>
			<xmax>272</xmax>
			<ymax>421</ymax>
		</bndbox>
	</object>
	<object>
		<name>M</name>
		<pose>Unspecified</pose>
		<truncated>0</truncated>
		<difficult>0</difficult>
		<bndbox>
			<xmin>394</xmin>
			<ymin>384</ymin>
			<xmax>457</xmax>
			<ymax>446</ymax>
		</bndbox>
	</object>
	<object>
		<name>M</name>
		<pose>Unspecified</pose>
		<truncated>0</truncated>
		<difficult>0</difficult>
		<bndbox>
			<xmin>396</xmin>
			<ymin>442</ymin>
			<xmax>448</xmax>
			<ymax>503</ymax>
		</bndbox>
	</object>
	<object>
		<name>M</name>
		<pose>Unspecified</pose>
		<truncated>0</truncated>
		<difficult>0</difficult>
		<bndbox>
			<xmin>424</xmin>
			<ymin>418</ymin>
			<xmax>468</xmax>
			<ymax>459</ymax>
		</bndbox>
	</object>
	<object>
		<name>M</name>
		<pose>Unspecified</pose>
		<truncated>0</truncated>
		<difficult>0</difficult>
		<bndbox>
			<xmin>441</xmin>
			<ymin>457</ymin>
			<xmax>478</xmax>
			<ymax>510</ymax>
		</bndbox>
	</object>
	<object>
		<name>M</name>
		<pose>Unspecified</pose>
		<truncated>0</truncated>
		<difficult>0</difficult>
		<bndbox>
			<xmin>531</xmin>
			<ymin>175</ymin>
			<xmax>566</xmax>
			<ymax>223</ymax>
		</bndbox>
	</object>
	<object>
		<name>M</name>
		<pose>Unspecified</pose>
		<truncated>0</truncated>
		<difficult>0</difficult>
		<bndbox>
			<xmin>559</xmin>
			<ymin>339</ymin>
			<xmax>599</xmax>
			<ymax>386</ymax>
		</bndbox>
	</object>
</annotation>
