<annotation>
	<folder>M</folder>
	<filename>gear2n_(12)_02_02.png</filename>
	<path>C:\Users\koiralaa\Desktop\ANNOTATIONS\test_splits_renamed\M\gear2n_(12)_02_02.png</path>
	<source>
		<database>Unknown</database>
	</source>
	<size>
		<width>612</width>
		<height>512</height>
		<depth>3</depth>
	</size>
	<segmented>0</segmented>
	<object>
		<name>M</name>
		<pose>Unspecified</pose>
		<truncated>0</truncated>
		<difficult>0</difficult>
		<bndbox>
			<xmin>198</xmin>
			<ymin>308</ymin>
			<xmax>243</xmax>
			<ymax>366</ymax>
		</bndbox>
	</object>
	<object>
		<name>M</name>
		<pose>Unspecified</pose>
		<truncated>0</truncated>
		<difficult>0</difficult>
		<bndbox>
			<xmin>314</xmin>
			<ymin>237</ymin>
			<xmax>360</xmax>
			<ymax>303</ymax>
		</bndbox>
	</object>
	<object>
		<name>M</name>
		<pose>Unspecified</pose>
		<truncated>0</truncated>
		<difficult>0</difficult>
		<bndbox>
			<xmin>470</xmin>
			<ymin>221</ymin>
			<xmax>524</xmax>
			<ymax>275</ymax>
		</bndbox>
	</object>
	<object>
		<name>M</name>
		<pose>Unspecified</pose>
		<truncated>0</truncated>
		<difficult>0</difficult>
		<bndbox>
			<xmin>484</xmin>
			<ymin>186</ymin>
			<xmax>538</xmax>
			<ymax>248</ymax>
		</bndbox>
	</object>
	<object>
		<name>M</name>
		<pose>Unspecified</pose>
		<truncated>0</truncated>
		<difficult>0</difficult>
		<bndbox>
			<xmin>443</xmin>
			<ymin>40</ymin>
			<xmax>487</xmax>
			<ymax>93</ymax>
		</bndbox>
	</object>
	<object>
		<name>M</name>
		<pose>Unspecified</pose>
		<truncated>0</truncated>
		<difficult>0</difficult>
		<bndbox>
			<xmin>498</xmin>
			<ymin>449</ymin>
			<xmax>530</xmax>
			<ymax>486</ymax>
		</bndbox>
	</object>
</annotation>
