<annotation>
	<folder>train_splits</folder>
	<filename>gear9n (45)_02_01.png</filename>
	<path>C:\Users\koiralaa\Desktop\ANNOTATIONS\train_splits\gear9n (45)_02_01.png</path>
	<source>
		<database>Unknown</database>
	</source>
	<size>
		<width>612</width>
		<height>512</height>
		<depth>3</depth>
	</size>
	<segmented>0</segmented>
	<object>
		<name>M</name>
		<pose>Unspecified</pose>
		<truncated>0</truncated>
		<difficult>0</difficult>
		<bndbox>
			<xmin>175</xmin>
			<ymin>443</ymin>
			<xmax>213</xmax>
			<ymax>486</ymax>
		</bndbox>
	</object>
</annotation>
